{
  "title": "testGame",
  "packageName": "org.cocos2d.demo",
  "startScene": "21730a77-f721-4377-9ed1-59e65ae6be2e",
  "excludeScenes": [],
  "orientation": {
    "landscapeRight": true,
    "landscapeLeft": true,
    "portrait": false,
    "upsideDown": false
  },
  "webOrientation": "auto",
  "inlineSpriteFrames": true,
  "inlineSpriteFrames_native": true,
  "mainCompressionType": "default",
  "mainIsRemote": false,
  "optimizeHotUpdate": false,
  "md5Cache": true,
  "nativeMd5Cache": true,
  "encryptJs": true,
  "xxteaKey": "d74ff771-a539-47",
  "zipCompressJs": true,
  "fb-instant-games": {},
  "android": {
    "packageName": "org.cocos2d.demo",
    "REMOTE_SERVER_ROOT": ""
  },
  "ios": {
    "packageName": "org.cocos2d.demo",
    "REMOTE_SERVER_ROOT": "",
    "ios_enable_jit": true
  },
  "mac": {
    "packageName": "org.cocos2d.demo",
    "REMOTE_SERVER_ROOT": "",
    "width": 1280,
    "height": 720
  },
  "win32": {
    "REMOTE_SERVER_ROOT": "",
    "width": 1280,
    "height": 720
  },
  "android-instant": {
    "packageName": "org.cocos2d.demo",
    "REMOTE_SERVER_ROOT": "",
    "pathPattern": "",
    "scheme": "https",
    "host": "",
    "skipRecord": false,
    "recordPath": ""
  },
  "harmonyos-next": {
    "packageName": "org.cocos2d.demo",
    "REMOTE_SERVER_ROOT": "",
    "jsEngine": "JSVM"
  },
  "appBundle": false,
  "agreements": {}
}
