[
  {
    "__type__": "cc.Prefab",
    "_name": "bubble",
    "_objFlags": 0,
    "_native": "",
    "data": {
      "__id__": 1
    },
    "optimizationPolicy": 0,
    "asyncLoadAssets": false,
    "readonly": false
  },
  {
    "__type__": "cc.Node",
    "_name": "bubble",
    "_objFlags": 0,
    "_parent": null,
    "_children": [],
    "_active": true,
    "_components": [
      {
        "__id__": 2
      },
      {
        "__id__": 4
      },
      {
        "__id__": 5
      }
    ],
    "_prefab": {
      "__id__": 6
    },
    "_opacity": 255,
    "_color": {
      "__type__": "cc.Color",
      "r": 255,
      "g": 255,
      "b": 255,
      "a": 255
    },
    "_contentSize": {
      "__type__": "cc.Size",
      "width": 100,
      "height": 112
    },
    "_anchorPoint": {
      "__type__": "cc.Vec2",
      "x": 0.5,
      "y": 0.5
    },
    "_trs": {
      "__type__": "TypedArray",
      "ctor": "Float64Array",
      "array": [
        524.726,
        290.881,
        0,
        0,
        0,
        0,
        1,
        1,
        1,
        1
      ]
    },
    "_eulerAngles": {
      "__type__": "cc.Vec3",
      "x": 0,
      "y": 0,
      "z": 0
    },
    "_skewX": 0,
    "_skewY": 0,
    "_is3DNode": false,
    "_groupIndex": 0,
    "groupIndex": 0,
    "_id": ""
  },
  {
    "__type__": "7e8c49UTsFKjL5kxek7bnbo",
    "_name": "",
    "_objFlags": 0,
    "node": {
      "__id__": 1
    },
    "_enabled": true,
    "bubbleSprites": {
      "__id__": 3
    },
    "destroySound": {
      "__uuid__": "7835edc7-1455-4088-adf3-b2580fef08e4"
    },
    "bombSound": {
      "__uuid__": "3bc6023e-bb0c-4076-94af-03e9266a59e3"
    },
    "_id": ""
  },
  {
    "__type__": "BubbleSpriteSet",
    "block_green": {
      "__uuid__": "e6ed0215-8179-4995-b12b-0046e7882348"
    },
    "block_blue": {
      "__uuid__": "9be9d1b8-e455-4c51-90d4-b59fb9e11e4b"
    },
    "block_purpure": {
      "__uuid__": "9bb8c614-e660-4ba3-b506-7c8caba67896"
    },
    "block_yellow": {
      "__uuid__": "0643a93b-e099-4770-8684-bcc7ae817a02"
    },
    "block_red": {
      "__uuid__": "8adfe279-0564-467d-9b5d-d23cb3b9e458"
    },
    "bomb": {
      "__uuid__": "5e271e44-5fa4-4ac2-9bb0-736577e50533"
    }
  },
  {
    "__type__": "cc.Sprite",
    "_name": "",
    "_objFlags": 0,
    "node": {
      "__id__": 1
    },
    "_enabled": true,
    "_materials": [
      {
        "__uuid__": "eca5d2f2-8ef6-41c2-bbe6-f9c79d09c432"
      }
    ],
    "_srcBlendFactor": 770,
    "_dstBlendFactor": 771,
    "_spriteFrame": {
      "__uuid__": "9be9d1b8-e455-4c51-90d4-b59fb9e11e4b"
    },
    "_type": 0,
    "_sizeMode": 1,
    "_fillType": 0,
    "_fillCenter": {
      "__type__": "cc.Vec2",
      "x": 0,
      "y": 0
    },
    "_fillStart": 0,
    "_fillRange": 0,
    "_isTrimmedMode": true,
    "_atlas": null,
    "_id": ""
  },
  {
    "__type__": "cc.Animation",
    "_name": "",
    "_objFlags": 0,
    "node": {
      "__id__": 1
    },
    "_enabled": true,
    "_defaultClip": null,
    "_clips": [
      {
        "__uuid__": "d98ce756-d467-4b48-ae86-866c443b5bff"
      },
      {
        "__uuid__": "4144651c-dabb-4b1c-a189-2366a4ed972d"
      }
    ],
    "playOnLoad": false,
    "_id": ""
  },
  {
    "__type__": "cc.PrefabInfo",
    "root": {
      "__id__": 1
    },
    "asset": {
      "__id__": 0
    },
    "fileId": "",
    "sync": false
  }
]